benchmarks/__init__.py
benchmarks/preprocessing_benchmarks.py
tests/analysis/__init__.py
tests/analysis/test_label.py
tests/analysis/test_location_identification.py
tests/analysis/test_metrics.py
tests/analysis/test_modal_split.py
tests/analysis/test_tracking_quality.py
tests/examples/__init__.py
tests/examples/test_examples.py
tests/examples/test_tutorial.py
tests/geogr/__init__.py
tests/geogr/test_distances.py
tests/geogr/test_filter.py
tests/io/__init__.py
tests/io/test_dataset_reader.py
tests/io/test_file.py
tests/io/test_from_geopandas.py
tests/io/test_postgis.py
tests/io/test_util.py
tests/model/__init__.py
tests/model/test_locations.py
tests/model/test_positionfixes.py
tests/model/test_staypoints.py
tests/model/test_tours.py
tests/model/test_triplegs.py
tests/model/test_trips.py
tests/model/test_util.py
tests/preprocessing/__init__.py
tests/preprocessing/test_positionfixes.py
tests/preprocessing/test_staypoints.py
tests/preprocessing/test_triplegs.py
tests/preprocessing/test_trips.py
tests/preprocessing/test_util.py
tests/visualization/__init__.py
tests/visualization/test_plotting.py
trackintel/__init__.py
trackintel/__version__.py
trackintel/core.py
trackintel/analysis/__init__.py
trackintel/analysis/labelling.py
trackintel/analysis/location_identification.py
trackintel/analysis/metrics.py
trackintel/analysis/modal_split.py
trackintel/analysis/tracking_quality.py
trackintel/geogr/__init__.py
trackintel/geogr/distances.py
trackintel/geogr/filter.py
trackintel/io/__init__.py
trackintel/io/dataset_reader.py
trackintel/io/file.py
trackintel/io/from_geopandas.py
trackintel/io/postgis.py
trackintel/io/util.py
trackintel/model/__init__.py
trackintel/model/locations.py
trackintel/model/positionfixes.py
trackintel/model/staypoints.py
trackintel/model/tours.py
trackintel/model/triplegs.py
trackintel/model/trips.py
trackintel/model/util.py
trackintel/preprocessing/__init__.py
trackintel/preprocessing/positionfixes.py
trackintel/preprocessing/staypoints.py
trackintel-1.4.2.dist-info/licenses/AUTHORS.md
trackintel-1.4.2.dist-info/licenses/LICENSE
trackintel-1.4.2.dist-info/METADATA
trackintel-1.4.2.dist-info/WHEEL
trackintel-1.4.2.dist-info/top_level.txt
trackintel-1.4.2.dist-info/RECORD
