Metadata-Version: 2.4
Name: trackintel
Version: 1.4.2
Summary: Human mobility and movement analysis framework.
Home-page: https://github.com/mie-lab/trackintel
Author: Dominik Bucher, Henry Martin, Ye Hong
Author-email: dobucher@ethz.ch, martinhe@ethz.ch, hongy@ethz.ch
License: MIT
Classifier: License :: OSI Approved :: MIT License
Classifier: Programming Language :: Python
Classifier: Programming Language :: Python :: 3
Classifier: Programming Language :: Python :: 3.6
Requires-Python: >=3.6.0
License-File: LICENSE
License-File: AUTHORS.md
Requires-Dist: pandas
Requires-Dist: geopandas>=0.12.0
Requires-Dist: matplotlib
Requires-Dist: numpy
Requires-Dist: shapely
Requires-Dist: geoalchemy2
Requires-Dist: osmnx
Requires-Dist: scikit-learn
Requires-Dist: tqdm
Requires-Dist: similaritymeasures
Dynamic: author
Dynamic: author-email
Dynamic: classifier
Dynamic: description
Dynamic: description-content-type
Dynamic: home-page
Dynamic: license
Dynamic: license-file
Dynamic: requires-dist
Dynamic: requires-python
Dynamic: summary
